apitomcp/__init__.py
apitomcp/__main__.py
apitomcp/auth.py
apitomcp/cli.py
apitomcp/config.py
apitomcp/generator.py
apitomcp/installer.py
apitomcp/runner.py
apitomcp/scraper.py
apitomcp/ui.py
apitomcp/validator.py
apitomcp-0.1.3.dist-info/METADATA
apitomcp-0.1.3.dist-info/WHEEL
apitomcp-0.1.3.dist-info/entry_points.txt
apitomcp-0.1.3.dist-info/licenses/LICENSE
apitomcp-0.1.3.dist-info/RECORD
