Metadata-Version: 2.4
Name: apitomcp
Version: 0.1.3
Summary: Convert any API documentation into an MCP server
Project-URL: Homepage, https://github.com/portoaj/api-to-mcp
Project-URL: Repository, https://github.com/portoaj/api-to-mcp
Author-email: Andrew Masek <andrewmasek@gmail.com>
License-Expression: MIT
License-File: LICENSE
Keywords: api,claude,cursor,llm,mcp,openapi
Classifier: Development Status :: 3 - Alpha
Classifier: Environment :: Console
Classifier: Intended Audience :: Developers
Classifier: License :: OSI Approved :: MIT License
Classifier: Programming Language :: Python :: 3.10
Classifier: Programming Language :: Python :: 3.11
Classifier: Programming Language :: Python :: 3.12
Classifier: Programming Language :: Python :: 3.13
Classifier: Topic :: Software Development :: Code Generators
Requires-Python: >=3.10
Requires-Dist: beautifulsoup4>=4.12.0
Requires-Dist: fastmcp>=2.0.0
Requires-Dist: httpx>=0.27.0
Requires-Dist: inquirerpy>=0.3.4
Requires-Dist: litellm>=1.40.0
Requires-Dist: markitdown>=0.1.0
Requires-Dist: openapi-spec-validator>=0.7.0
Requires-Dist: rich>=13.0.0
Requires-Dist: typer>=0.9.0
